{
    "results": [
        {
            "contents": [
                {
                    "category": "business",
                    "content": "News Corp, the media company controlled by Australian billionaire Rupert Murdoch, is eyeing a move into the video games market.",
                    "image_url": null
                }
            ],
            "thumbnail_url": null,
            "title": "News Corp eyes video games market"
        },
        {
            "contents": [
                {
                    "category": "business",
                    "content": "Yahoo has reached the grand old age of 10 and, in internet years, that is a long time. For many, Yahoo remains synonymous with the internet - a veteran that managed to ride the dot-com wave and the subsequent crash and maintain itself as one of the web's top brands.",
                    "image_url": null
                },
                {
                    "category": "business",
                    "content": "The game is theirs to lose and MSN is the only one that stands in the way of Yahoo's domination.",
                    "image_url": null
                }
            ],
            "thumbnail_url": null,
            "title": "Can Yahoo dominate next decade?"
        },
        {
            "contents": [
                {
                    "category": "business",
                    "content": "For Jupiter analyst Olivier Beauvillain, Yahoo's initial decision to put its investment on search on hold was an error.",
                    "image_url": null
                },
                {
                    "category": "business",
                    "content": "Search technology is valuable but the next generation of search is going to be about premium content and the interface that users have to that content.",
                    "image_url": null
                }
            ],
            "thumbnail_url": null,
            "title": "Yahoo dominates next decade"
        },
        {
            "contents": [
                {
                    "category": "business",
                    "content": "Yahoo is a canny combination of acquisitions such as that of Inktomi and Overture, and by avoiding direct involvement in either content creation or internet access.",
                    "image_url": null
                }
            ],
            "thumbnail_url": null,
            "title": "News Corp reaches grand old age"
        },
        {
            "contents": [
                {
                    "category": "business",
                    "content": "About 50,000 new products will be unleashed at the tech-fest, which is the largest yet.",
                    "image_url": null
                }
            ],
            "thumbnail_url": null,
            "title": "CES features several more key speeches from major technology players"
        },
        {
            "contents": [
                {
                    "category": "business",
                    "content": "Gaming is becoming more of a social thing and all of the social genres will use this rich communications.",
                    "image_url": null
                }
            ],
            "thumbnail_url": null,
            "title": "Google's latest innovation"
        },
        {
            "contents": [
                {
                    "category": "business",
                    "content": "Video games are proving almost as profitable as they are fun.",
                    "image_url": null
                }
            ],
            "thumbnail_url": null,
            "title": "Microsoft's gaming ambitions"
        },
        {
            "contents": [
                {
                    "category": "business",
                    "content": "Nick Hazel, Yahoo's head of consumer services in the UK, thinks Yahoo's vision of becoming the ultimate gateway to the web will move increasing towards movies and television.",
                    "image_url": null
                }
            ],
            "thumbnail_url": null,
            "title": "Yahoo Messenger coming to mobiles"
        },
        {
            "contents": [
                {
                    "category": "business",
                    "content": "Allen Weiner, a research director at Gartner and someone who has followed Yahoo's progress since the early years.",
                    "image_url": null
                }
            ],
            "thumbnail_url": null,
            "title": "Gartner says Google is not a threat"
        },
        {
            "contents": [
                {
                    "category": "business",
                    "content": "The company is planning to provide a range of services beyond the desktop.",
                    "image_url": null
                }
            ],
            "thumbnail_url": null,
            "title": "Yahoo's vision of the future"
        }
    ],
    "time_taken": 76.6
}